ezml/__init__.py
ezml/__main__.py
ezml/interpreting.py
ezml/preprocessing.py
tests/__init__.py
ez_ml-0.1.3.dist-info/LICENSE
ez_ml-0.1.3.dist-info/METADATA
ez_ml-0.1.3.dist-info/WHEEL
ez_ml-0.1.3.dist-info/entry_points.txt
ez_ml-0.1.3.dist-info/top_level.txt
ez_ml-0.1.3.dist-info/RECORD
