Metadata-Version: 2.1
Name: ez-ml
Version: 0.1.3
Summary: Most useful ML lib
Home-page: http://www.github.com/ghazibendahmen/ez-ml
Author: Ghazi Ben Dahmen
Author-email: ghazi.ben.dahmen3@gmail.com
License: UNKNOWN
Platform: UNKNOWN
Classifier: Programming Language :: Python :: 3
Classifier: License :: OSI Approved :: MIT License
Classifier: Operating System :: OS Independent
Requires-Dist: pandas
Requires-Dist: sklearn
Requires-Dist: matplotlib
